curltopy/__init__.py
curltopy/convert.py
curltopy-0.1.2.data/scripts/curltopy
curltopy-0.1.2.dist-info/METADATA
curltopy-0.1.2.dist-info/RECORD
curltopy-0.1.2.dist-info/WHEEL
curltopy-0.1.2.dist-info/top_level.txt
