Metadata-Version: 2.1
Name: curltopy
Version: 0.1.2
Summary: Converts curl statements to python using command line
Home-page: https://github.com/nitrocode/curl2.py
Author: UNKNOWN
Author-email: UNKNOWN
License: UNKNOWN
Platform: UNKNOWN
